Metadata-Version: 2.4
Name: fdemmer-django-all-access
Version: 1.4.0
Summary: django-all-access is a reusable application for user registration and authentication from OAuth 1.0 and OAuth 2.0 providers such as Twitter and Facebook.
Home-page: https://github.com/fdemmer/django-all-access
Download-URL: https://github.com/fdemmer/django-all-access/archive/v1.4.0.tar.gz
Author: Florian Demmer
Author-email: fdemmer@gmail.com
License: BSD
Project-URL: Changelog, https://github.com/fdemmer/django-all-access/blob/v1.4.0/docs/releases.rst
Classifier: Development Status :: 5 - Production/Stable
Classifier: Environment :: Web Environment
Classifier: Framework :: Django
Classifier: Framework :: Django :: 3.2
Classifier: Framework :: Django :: 4.2
Classifier: Framework :: Django :: 5.0
Classifier: Framework :: Django :: 5.1
Classifier: Framework :: Django :: 5.2
Classifier: Intended Audience :: Developers
Classifier: License :: OSI Approved :: BSD License
Classifier: Natural Language :: English
Classifier: Operating System :: OS Independent
Classifier: Programming Language :: Python
Classifier: Programming Language :: Python :: 3 :: Only
Classifier: Programming Language :: Python :: 3
Classifier: Programming Language :: Python :: 3.8
Classifier: Programming Language :: Python :: 3.9
Classifier: Programming Language :: Python :: 3.10
Classifier: Programming Language :: Python :: 3.11
Classifier: Programming Language :: Python :: 3.12
Classifier: Programming Language :: Python :: 3.13
Classifier: Topic :: Internet :: WWW/HTTP :: Dynamic Content
Classifier: Topic :: Software Development :: Libraries :: Python Modules
Requires-Python: >=3.8
License-File: LICENSE
License-File: AUTHORS
Requires-Dist: Django>=3.2
Requires-Dist: pycryptodome>=3.9
Requires-Dist: requests>=2.0
Requires-Dist: requests_oauthlib>=0.4.2
Requires-Dist: oauthlib>=0.6.2
Provides-Extra: cov
Requires-Dist: coverage[toml]~=6.0; extra == "cov"
Provides-Extra: docs
Requires-Dist: sphinx; extra == "docs"
Dynamic: author
Dynamic: author-email
Dynamic: classifier
Dynamic: description
Dynamic: download-url
Dynamic: home-page
Dynamic: license
Dynamic: license-file
Dynamic: project-url
Dynamic: provides-extra
Dynamic: requires-dist
Dynamic: requires-python
Dynamic: summary
